MANIFEST.in
README.md
setup.py
TMFrame/__init__.py
TMFrame/__main__.py
TMFrame/data1
TMFrame/not.png
TMFrame.egg-info/PKG-INFO
TMFrame.egg-info/SOURCES.txt
TMFrame.egg-info/dependency_links.txt
TMFrame.egg-info/requires.txt
TMFrame.egg-info/top_level.txt
TMFrame/font/FreeSerifItalic.ttf
example/maxresdefault.jpg
example/result.jpg