Metadata-Version: 2.1
Name: TMFrame
Version: 0.0.1.dev3
Summary: Music Thumbnail Maker
Home-page: https://github.com/krypton-byte/MFrame
Author: Krypton Byte
Author-email: galaxyvplus6434@gmail.com
License: MIT
Keywords: Thumbnail,Music,Maker
Platform: UNKNOWN
Classifier: Development Status :: 3 - Alpha
Classifier: Intended Audience :: Developers
Classifier: Topic :: Software Development :: Build Tools
Classifier: License :: OSI Approved :: MIT License
Classifier: Programming Language :: Python :: 3.8
Classifier: Programming Language :: Python :: 3.9
